MANIFEST.in
README.md
copyAssets.py
package.json
pyproject.toml
setup.cfg
setup.py
jupyter_server_config.d/jupyter_server_itables.json
jupyterlab_itables/__init__.py
jupyterlab_itables/app.py
jupyterlab_itables.egg-info/PKG-INFO
jupyterlab_itables.egg-info/SOURCES.txt
jupyterlab_itables.egg-info/dependency_links.txt
jupyterlab_itables.egg-info/not-zip-safe
jupyterlab_itables.egg-info/requires.txt
jupyterlab_itables.egg-info/top_level.txt
jupyterlab_itables/static/datatables.net/License.txt
jupyterlab_itables/static/datatables.net/Readme.md
jupyterlab_itables/static/datatables.net/package.json
jupyterlab_itables/static/datatables.net-dt/License.txt
jupyterlab_itables/static/datatables.net-dt/Readme.md
jupyterlab_itables/static/datatables.net-dt/package.json
jupyterlab_itables/static/datatables.net-dt/css/jquery.dataTables.css
jupyterlab_itables/static/datatables.net-dt/css/jquery.dataTables.min.css
jupyterlab_itables/static/datatables.net-dt/images/favicon.ico
jupyterlab_itables/static/datatables.net-dt/images/sort_asc.png
jupyterlab_itables/static/datatables.net-dt/images/sort_asc_disabled.png
jupyterlab_itables/static/datatables.net-dt/images/sort_both.png
jupyterlab_itables/static/datatables.net-dt/images/sort_desc.png
jupyterlab_itables/static/datatables.net-dt/images/sort_desc_disabled.png
jupyterlab_itables/static/datatables.net-dt/js/dataTables.dataTables.js
jupyterlab_itables/static/datatables.net-dt/js/dataTables.dataTables.min.js
jupyterlab_itables/static/datatables.net-dt/types/dataTables.dataTables.d.ts
jupyterlab_itables/static/datatables.net/js/jquery.dataTables.js
jupyterlab_itables/static/datatables.net/js/jquery.dataTables.min.js
jupyterlab_itables/static/datatables.net/js/jquery.dataTables.mjs
jupyterlab_itables/static/datatables.net/types/types.d.ts
jupyterlab_itables/static/jquery/.editorconfig
jupyterlab_itables/static/jquery/.eslintignore
jupyterlab_itables/static/jquery/.eslintrc-browser.json
jupyterlab_itables/static/jquery/.eslintrc-node.json
jupyterlab_itables/static/jquery/.eslintrc.json
jupyterlab_itables/static/jquery/.gitattributes
jupyterlab_itables/static/jquery/.gitignore
jupyterlab_itables/static/jquery/.mailmap
jupyterlab_itables/static/jquery/.npmignore
