Metadata-Version: 2.1
Name: jupyterlab-itables
Version: 0.1.0
Summary: ITables resources as a Jupyter Server Extension.
Home-page: http://github.com/mwouts/jupyterlab-itables/
Author: Marc Wouts
Author-email: marc.wouts@gmail.com
License: BSD 3-Clause License
Keywords: ipython,jupyter,jupyter-server,datatables
Platform: Linux
Platform: Mac OS X
Platform: Windows
Classifier: Framework :: Jupyter
Classifier: Intended Audience :: Developers
Classifier: Intended Audience :: System Administrators
Classifier: Intended Audience :: Science/Research
Classifier: Programming Language :: Python
Classifier: Programming Language :: Python :: 3
Classifier: Programming Language :: Python :: 3.6
Classifier: Programming Language :: Python :: 3.7
Classifier: Programming Language :: Python :: 3.8
Classifier: Programming Language :: Python :: 3.9
Classifier: Programming Language :: Python :: 3.10
Requires-Python: >=3.6
